Metadata-Version: 1.0
Name: etch-distributionsu
Version: 0.1
Summary: Binomial & Gaussian distributions
Home-page: UNKNOWN
Author: Ahmed Hesham
Author-email: UNKNOWN
License: UNKNOWN
Platform: UNKNOWN
